[{"title":"Honorable","first_name":"Catrina","last_name":"Athersmith","email":"cathersmith0@eepurl.com","gender":"Female","rodne_cislo":"9656281789","job_title":"Programmer Analyst IV"},
  {"title":"Dr","first_name":"Sisely","last_name":"Jardine","email":"sjardine1@samsung.com","gender":"Female","rodne_cislo":"9051163979","job_title":"VP Sales"},
  {"title":"Mr","first_name":"Alanna","last_name":"Bauld","email":"abauld2@qq.com","gender":"Female","rodne_cislo":"9957138906","job_title":"Budget/Accounting Analyst III"},
  {"title":"Honorable","first_name":"Farand","last_name":"Fewlass","email":"ffewlass3@163.com","gender":"Female","rodne_cislo":"9858022449","job_title":"Associate Professor"},
  {"title":"Rev","first_name":"Giordano","last_name":"Eusden","email":"geusden4@ft.com","gender":"Male","rodne_cislo":"9507130391","job_title":"Senior Editor"},
  {"title":"Mr","first_name":"Wang","last_name":"Ambroz","email":"wambroz5@wiley.com","gender":"Male","rodne_cislo":"9910096515","job_title":"VP Accounting"},
  {"title":"Mr","first_name":"Montgomery","last_name":"Dermott","email":"mdermott6@opera.com","gender":"Male","rodne_cislo":"9609103636","job_title":"Legal Assistant"},
  {"title":"Rev","first_name":"Nicolas","last_name":"Matcham","email":"nmatcham7@paginegialle.it","gender":"Male","rodne_cislo":"9201209248","job_title":"Graphic Designer"},
  {"title":"Mrs","first_name":"Marlow","last_name":"Ozintsev","email":"mozintsev8@cafepress.com","gender":"Male","rodne_cislo":"9801123024","job_title":"Structural Engineer"},
  {"title":"Honorable","first_name":"Georgetta","last_name":"Gostall","email":"ggostall9@webmd.com","gender":"Female","rodne_cislo":"9552025340","job_title":"Technical Writer"}]